{
    "code": 0,
    "msg": "",
    "data": {
        "zyzb": {
            "date": "2020中报",
            "detail": {
                "date": "2020中报",
                "mgsy": "0.80元",
                "jlr": "17.00亿元",
                "jlrzzl": "64.53%",
                "yyzsr": "79.89亿元",
                "zsrzzl": "31.59%",
                "mgjzc": "3.88元",
                "sy": "16.15亿元",
                "jzc": "81.90亿元",
                "sy_jzc": "19.72%",
                "jzcsyl": "22.05%",
                "zcfzl": "31.67%",
                "syl": "26.15",
                "sjl": "9.63"
            }
        },
        "gsjj": {
            "gsmz": "芜湖三七互娱网络科技集团股份有限公司",
            "yw": "手机游戏和网页游戏的研发、发行和运营。",
            "dy": "安徽",
            "jg": "35.000元",
            "riqi": "2011-03-02",
            "plate": [{
                    "name": "传媒",
                    "id": "01801760",
                    "level": "1"
                },
                {
                    "name": "互联网传媒",
                    "id": "01801752",
                    "level": "2"
                }
            ],
            "concept": [{
                    "name": "文化传媒",
                    "id": "02002486"
                },
                {
                    "name": "在线教育",
                    "id": "02003662"
                },
                {
                    "name": "手游概念",
                    "id": "02003642"
                },
                {
                    "name": "虚拟现实",
                    "id": "02003722"
                },
                {
                    "name": "深股通",
                    "id": "02003804"
                },
                {
                    "name": "转融券标的",
                    "id": "02003631"
                },
                {
                    "name": "创投",
                    "id": "02003506"
                },
                {
                    "name": "网络游戏",
                    "id": "02003509"
                },
                {
                    "name": "MSCI概念",
                    "id": "02031027"
                },
                {
                    "name": "融资融券",
                    "id": "02003596"
                },
                {
                    "name": "参股新三板",
                    "id": "02003600"
                }
            ],
            "area": [{
                "name": "安徽",
                "id": "03001149"
            }]
        },
        "zysr": [{
                "date": "2020中报",
                "detail": [{
                        "type": "sector",
                        "detail": [{
                            "name": "网络游戏行业",
                            "unit": "元",
                            "income": "79.89亿",
                            "zb": "100.00"
                        }]
                    },
                    {
                        "type": "region",
                        "detail": [{
                                "name": "境内",
                                "unit": "元",
                                "income": "70.20亿",
                                "zb": "87.87"
                            },
                            {
                                "name": "境外",
                                "unit": "元",
                                "income": "9.69亿",
                                "zb": "12.13"
                            }
                        ]
                    },
                    {
                        "type": "product",
                        "detail": [{
                                "name": "手机游戏",
                                "unit": "元",
                                "income": "74.12亿",
                                "zb": "92.78"
                            },
                            {
                                "name": "网页游戏",
                                "unit": "元",
                                "income": "5.65亿",
                                "zb": "7.07"
                            },
                            {
                                "name": "其他",
                                "unit": "元",
                                "income": "1154.69万",
                                "zb": "0.14"
                            }
                        ]
                    }
                ]
            },
            {
                "date": "2019年报",
                "detail": [{
                        "type": "sector",
                        "detail": [{
                            "name": "网络游戏行业",
                            "unit": "元",
                            "income": "132.27亿",
                            "zb": "100.00"
                        }]
                    },
                    {
                        "type": "region",
                        "detail": [{
                                "name": "境内",
                                "unit": "元",
                                "income": "121.79亿",
                                "zb": "92.07"
                            },
                            {
                                "name": "境外",
                                "unit": "元",
                                "income": "10.49亿",
                                "zb": "7.93"
                            }
                        ]
                    },
                    {
                        "type": "product",
                        "detail": [{
                                "name": "移动游戏",
                                "unit": "元",
                                "income": "119.89亿",
                                "zb": "90.64"
                            },
                            {
                                "name": "网页游戏",
                                "unit": "元",
                                "income": "12.32亿",
                                "zb": "9.31"
                            },
                            {
                                "name": "其他",
                                "unit": "元",
                                "income": "692.50万",
                                "zb": "0.05"
                            }
                        ]
                    }
                ]
            },
            {
                "date": "2019中报",
                "detail": [{
                        "type": "sector",
                        "detail": [{
                            "name": "网络游戏行业",
                            "unit": "元",
                            "income": "60.71亿",
                            "zb": "100.00"
                        }]
                    },
                    {
                        "type": "region",
                        "detail": [{
                                "name": "境内",
                                "unit": "元",
                                "income": "55.74亿",
                                "zb": "91.81"
                            },
                            {
                                "name": "境外",
                                "unit": "元",
                                "income": "4.97亿",
                                "zb": "8.19"
                            }
                        ]
                    },
                    {
                        "type": "product",
                        "detail": [{
                                "name": "手机游戏",
                                "unit": "元",
                                "income": "54.27亿",
                                "zb": "89.39"
                            },
                            {
                                "name": "网页游戏",
                                "unit": "元",
                                "income": "6.44亿",
                                "zb": "10.61"
                            }
                        ]
                    }
                ]
            },
            {
                "date": "2018年报",
                "detail": [{
                        "type": "sector",
                        "detail": [{
                                "name": "网络游戏行业",
                                "unit": "元",
                                "income": "72.47亿",
                                "zb": "94.95"
                            },
                            {
                                "name": "汽车零部件行业",
                                "unit": "元",
                                "income": "3.85亿",
                                "zb": "5.05"
                            }
                        ]
                    },
                    {
                        "type": "region",
                        "detail": [{
                                "name": "国内",
                                "unit": "元",
                                "income": "67.06亿",
                                "zb": "87.86"
                            },
                            {
                                "name": "海外",
                                "unit": "元",
                                "income": "9.27亿",
                                "zb": "12.14"
                            }
                        ]
                    },
                    {
                        "type": "product",
                        "detail": [{
                                "name": "手机游戏",
                                "unit": "元",
                                "income": "55.82亿",
                                "zb": "73.13"
                            },
                            {
                                "name": "网页游戏",
                                "unit": "元",
                                "income": "16.46亿",
                                "zb": "21.56"
                            },
                            {
                                "name": "汽车零部件",
                                "unit": "元",
                                "income": "3.85亿",
                                "zb": "5.05"
                            },
                            {
                                "name": "其他",
                                "unit": "元",
                                "income": "1973.93万",
                                "zb": "0.26"
                            }
                        ]
                    }
                ]
            },
            {
                "date": "2018中报",
                "detail": [{
                        "type": "sector",
                        "detail": [{
                                "name": "网络游戏行业",
                                "unit": "元",
                                "income": "30.71亿",
                                "zb": "92.99"
                            },
                            {
                                "name": "汽车零部件行业",
                                "unit": "元",
                                "income": "2.31亿",
                                "zb": "7.01"
                            }
                        ]
                    },
                    {
                        "type": "region",
                        "detail": [{
                                "name": "国内",
                                "unit": "元",
                                "income": "28.28亿",
                                "zb": "85.64"
                            },
                            {
                                "name": "海外",
                                "unit": "元",
                                "income": "4.74亿",
                                "zb": "14.36"
                            }
                        ]
                    },
                    {
                        "type": "product",
                        "detail": [{
                                "name": "手机游戏",
                                "unit": "元",
                                "income": "21.46亿",
                                "zb": "64.97"
                            },
                            {
                                "name": "网页游戏",
                                "unit": "元",
                                "income": "9.10亿",
                                "zb": "27.56"
                            },
                            {
                                "name": "汽车零部件",
                                "unit": "元",
                                "income": "2.31亿",
                                "zb": "7.01"
                            },
                            {
                                "name": "其他",
                                "unit": "元",
                                "income": "1527.54万",
                                "zb": "0.46"
                            }
                        ]
                    }
                ]
            },
            {
                "date": "2017年报",
                "detail": [{
                        "type": "sector",
                        "detail": [{
                                "name": "网络游戏行业",
                                "unit": "元",
                                "income": "56.29亿",
                                "zb": "90.95"
                            },
                            {
                                "name": "汽车零部件行业",
                                "unit": "元",
                                "income": "5.60亿",
                                "zb": "9.05"
                            }
                        ]
                    },
                    {
                        "type": "region",
                        "detail": [{
                                "name": "国内",
                                "unit": "元",
                                "income": "52.69亿",
                                "zb": "85.14"
                            },
                            {
                                "name": "海外",
                                "unit": "元",
                                "income": "9.20亿",
                                "zb": "14.86"
                            }
                        ]
                    },
                    {
                        "type": "product",
                        "detail": [{
                                "name": "手机游戏",
                                "unit": "元",
                                "income": "32.84亿",
                                "zb": "53.06"
                            },
                            {
                                "name": "网页游戏",
                                "unit": "元",
                                "income": "22.99亿",
                                "zb": "37.15"
                            },
                            {
                                "name": "汽车零部件",
                                "unit": "元",
                                "income": "5.60亿",
                                "zb": "9.05"
                            },
                            {
                                "name": "其它",
                                "unit": "元",
                                "income": "4613.34万",
                                "zb": "0.75"
                            }
                        ]
                    }
                ]
            }
        ],
        "gdgb": {
            "zgb": "21.12亿股",
            "ltgb": "14.80亿股",
            "gdrshb": "2.63",
            "rjcg": "3.77万股",
            "gdrs": "5.60万户",
            "ltgdzb": "26.51",
            "gdzb": "59.39"
        },
        "ggzjc": [{
                "date": "2020-06-09",
                "gg": "曾开天",
                "bdl": "-101.72万",
                "jj": "33.08"
            },
            {
                "date": "2020-05-22",
                "gg": "曾开天",
                "bdl": "-68万",
                "jj": "32.45"
            },
            {
                "date": "2020-05-21",
                "gg": "曾开天",
                "bdl": "-1425万",
                "jj": "32.45"
            }
        ],
        "ggjj": [{
                "gg": "李卫伟",
                "zw": "总经理,董事长,非独立董事",
                "cgs": "4.04亿",
                "xc": "219万"
            },
            {
                "gg": "曾开天",
                "zw": "副董事长,非独立董事",
                "cgs": "2.45亿",
                "xc": "245万"
            },
            {
                "gg": "叶威",
                "zw": "董事会秘书,财务总监",
                "cgs": "--",
                "xc": "140万"
            }
        ],
        "fhsp": [{
                "nd": "2020",
                "date": "2020-09-18",
                "type": "",
                "sg": "0",
                "zz": "0",
                "fh": "3",
                "djr": "2020-09-24",
                "cqr": "2020-09-25"
            },
            {
                "nd": "2019",
                "date": "2020-04-29",
                "type": "",
                "sg": "0",
                "zz": "0",
                "fh": "3",
                "djr": "2020-05-08",
                "cqr": "2020-05-11"
            },
            {
                "nd": "2019",
                "date": "2019-09-19",
                "type": "",
                "sg": "0",
                "zz": "0",
                "fh": "1",
                "djr": "2019-09-25",
                "cqr": "2019-09-26"
            },
            {
                "nd": "2018",
                "date": "2019-07-10",
                "type": "",
                "sg": "0",
                "zz": "0",
                "fh": "2",
                "djr": "2019-07-15",
                "cqr": "2019-07-16"
            },
            {
                "nd": "2018",
                "date": "2018-09-20",
                "type": "",
                "sg": "0",
                "zz": "0",
                "fh": "1",
                "djr": "2018-09-26",
                "cqr": "2018-09-27"
            },
            {
                "nd": "2017",
                "date": "2018-06-28",
                "type": "",
                "sg": "0",
                "zz": "0",
                "fh": "1",
                "djr": "2018-07-04",
                "cqr": "2018-07-05"
            },
            {
                "nd": "2017",
                "date": "2017-08-31",
                "type": "",
                "sg": "0",
                "zz": "0",
                "fh": "0",
                "djr": "-",
                "cqr": "-"
            },
            {
                "nd": "2016",
                "date": "2017-05-17",
                "type": "",
                "sg": "0",
                "zz": "0",
                "fh": "1",
                "djr": "2017-05-23",
                "cqr": "2017-05-24"
            },
            {
                "nd": "2016",
                "date": "2016-08-23",
                "type": "",
                "sg": "0",
                "zz": "0",
                "fh": "0",
                "djr": "-",
                "cqr": "-"
            },
            {
                "nd": "2015",
                "date": "2016-05-31",
                "type": "",
                "sg": "0",
                "zz": "10",
                "fh": "1",
                "djr": "2016-06-03",
                "cqr": "2016-06-06"
            }
        ],
        "pxmzb": {
            "pxmzb": "41.96",
            "px": "2751155775.5",
            "fx": "595000000",
            "zf": "5960864914",
            "pg": "0",
            "no": [
                "10",
                "60"
            ]
        },
        "hydb": {
            "date": "2020中报",
            "hyname": "互联网传媒",
            "stock": {
                "stockcode": "002555",
                "date": "2020-06-30",
                "industry": "01801752",
                "mgsy": "0.80",
                "yysr": "7988675195.57",
                "jlr": "1699736123.46",
                "mgjzc": "3.88",
                "jzcsyl": "22.05",
                "sc": "sz",
                "create_time": "2020-09-18 21:23:08",
                "f_mgsy": "0.8000",
                "f_yysr": "79.89亿",
                "f_jlr": "17.00亿",
                "f_mgjzc": "3.8800",
                "f_jzcsyl": "22.05",
                "stockname": "三七互娱"
            },
            "hy": {
                "mgsy": "0.3446",
                "yysr": "1683510740.51",
                "jlr": "228107261.22",
                "mgjzc": "4.7734",
                "jzcsyl": "5.82",
                "f_mgsy": "0.3446",
                "f_yysr": "16.84亿",
                "f_jlr": "2.28亿",
                "f_mgjzc": "4.7734",
                "f_jzcsyl": "5.82"
            },
            "hymax": {
                "mgsy": "7.67",
                "yysr": "24008862573.43",
                "jlr": "3674939672.22",
                "mgjzc": "46.00",
                "jzcsyl": "55.16"
            },
            "hymin": {
                "mgsy": "-2.74",
                "yysr": "6848815.67",
                "jlr": "-1578629810.42",
                "mgjzc": "-1.22",
                "jzcsyl": "-26.73"
            }
        },
        "hytrend": [{
                "date": "2019",
                "yyzsr": "132.27亿元",
                "t_yyzsr": "73.30",
                "f_yyzsr": "13227000000",
                "jlr": "21.15亿元",
                "t_jlr": "109.69",
                "f_jlr": "2115000000",
                "mgsy": "1.00元",
                "t_mgsy": "112.77",
                "f_mgsy": "1"
            },
            {
                "date": "2018",
                "yyzsr": "76.33亿元",
                "t_yyzsr": "23.33",
                "f_yyzsr": "7633000000",
                "jlr": "10.09亿元",
                "t_jlr": "-37.77",
                "f_jlr": "1009000000",
                "mgsy": "0.47元",
                "t_mgsy": "-38.16",
                "f_mgsy": "0.47"
            },
            {
                "date": "2017",
                "yyzsr": "61.89亿元",
                "t_yyzsr": "17.93",
                "f_yyzsr": "6189000000",
                "jlr": "16.21亿元",
                "t_jlr": "51.43",
                "f_jlr": "1621000000",
                "mgsy": "0.76元",
                "t_mgsy": "49.02",
                "f_mgsy": "0.76"
            },
            {
                "date": "2016",
                "yyzsr": "52.48亿元",
                "t_yyzsr": "12.69",
                "f_yyzsr": "5248000000",
                "jlr": "10.70亿元",
                "t_jlr": "111.49",
                "f_jlr": "1070000000",
                "mgsy": "0.51元",
                "t_mgsy": "75.86",
                "f_mgsy": "0.51"
            }
        ]
    }
}