{
    "publisherData": {
        "modelId": "90417",
        "name": "Dreamscape Media Video",
        "url": "https://www.dreamscapeab.com/home",
        "checkout": 0,
        "educationalEnabled": 1,
        "dateModified": 1558735528
    },
    "epub": null,
    "timePerPage": 2,
    "book": {
        "modelId": "63107",
        "id": "63107",
        "title": "Terrific",
        "author": "Jon Agee",
        "illustrator": " ",
        "numPages": 0,
        "bookDescription": "A cynical, unlucky curmudgeon becomes shipwrecked with a very helpful parrot.",
        "coverColorR": 210,
        "coverColorG": 210,
        "coverColorB": 206,
        "version": 2147483647,
        "previewPercent": 20,
        "publisher": "Dreamscape Media Video",
        "publisherId": "90417",
        "age": 6,
        "pageNumOffset": 0,
        "active": 1,
        "audio": 0,
        "lexile": "510L",
        "avgTime": "--",
        "avgTimeInt": 0,
        "ar": "2.5",
        "fandp": "-",
        "dra": "-",
        "gr": "-",
        "language": 1,
        "rating": 75,
        "type": 4,
        "subject": "90",
        "subjectDesc": "Overcoming Challenges",
        "subjectColor": "48D864",
        "copyright": "",
        "aspectRatio": 0,
        "contentHash": "",
        "payPerView": 0,
        "highlightingEnabled": 0,
        "highlightingStatus": "0",
        "panelStatus": 0,
        "date_modified": 1555374982,
        "duration": 427
    },
    "userBook": {
        "modelId": "46250489-63107",
        "userId": "46250489",
        "bookId": "63107",
        "currentPageIndex": 0,
        "farthestPageIndex": 0,
        "favorited": 0,
        "finishTime": 0,
        "paid": 0,
        "progress": 0,
        "rated": 0,
        "rating": 0,
        "readTime": 0,
        "recommended": 0,
        "lastModified": 1559309893,
        "bookmarks": "",
        "timesCompleted": 0,
        "currentReadTime": 0,
        "dateModified": 1559309893,
        "book": {
            "modelId": "63107",
            "title": "Terrific",
            "type": 4,
            "active": 1,
            "audio": 0,
            "contentHash": ""
        }
    },
    "quiz": null
}