{
    "publisherData": {
        "modelId": "90176",
        "name": "KidLit TV",
        "url": "http://kidlit.tv/",
        "checkout": 0,
        "educationalEnabled": 1,
        "dateModified": 1523404338
    },
    "epub": null,
    "timePerPage": 2,
    "book": {
        "modelId": "63995",
        "id": "63995",
        "title": "Ready Set Draw: The Boy from Swap!",
        "author": "KidLit TV",
        "illustrator": " ",
        "numPages": 0,
        "bookDescription": "Steve Light is back with another episode of Ready Set Draw! On this episode find out how to draw the little boy from his picture book SWAP!",
        "coverColorR": 170,
        "coverColorG": 198,
        "coverColorB": 209,
        "version": 2147483647,
        "previewPercent": 20,
        "publisher": "KidLit TV",
        "publisherId": "90176",
        "age": 5,
        "pageNumOffset": 0,
        "active": 1,
        "audio": 0,
        "lexile": "-",
        "avgTime": "--",
        "avgTimeInt": 0,
        "ar": "-",
        "fandp": "-",
        "dra": "-",
        "gr": "-",
        "language": 1,
        "rating": 75,
        "type": 4,
        "subject": "87",
        "subjectDesc": "Arts, Crafts, DIY",
        "subjectColor": "956FCD",
        "copyright": "",
        "aspectRatio": 0,
        "contentHash": "",
        "payPerView": 0,
        "highlightingEnabled": 0,
        "highlightingStatus": "0",
        "panelStatus": 0,
        "date_modified": 1556756874,
        "duration": 214
    },
    "userBook": {
        "modelId": "46250489-63995",
        "userId": "46250489",
        "bookId": "63995",
        "currentPageIndex": 0,
        "farthestPageIndex": 0,
        "favorited": 0,
        "finishTime": 0,
        "paid": 0,
        "progress": 0,
        "rated": 0,
        "rating": 0,
        "readTime": 0,
        "recommended": 0,
        "lastModified": 1559309894,
        "bookmarks": "",
        "timesCompleted": 0,
        "currentReadTime": 0,
        "dateModified": 1559309894,
        "book": {
            "modelId": "63995",
            "title": "Ready Set Draw: The Boy from Swap!",
            "type": 4,
            "active": 1,
            "audio": 0,
            "contentHash": ""
        }
    },
    "quiz": null
}